lxparse/__init__.py
lxparse/lxparse.py
lxparse/parsepack/__init__.py
lxparse/parsepack/parse_author.py
lxparse/parsepack/parse_content.py
lxparse/parsepack/parse_date.py
lxparse/parsepack/parse_list.py
lxparse/parsepack/parse_loc.py
lxparse/parsepack/parse_title.py
lxparse/readability/__init__.py
lxparse/readability/cleaners.py
lxparse/readability/debug.py
lxparse/readability/encoding.py
lxparse/readability/htmls.py
lxparse/readability/readability.py
lxparse-1.0.8.dist-info/LICENSE.txt
lxparse-1.0.8.dist-info/METADATA
lxparse-1.0.8.dist-info/WHEEL
lxparse-1.0.8.dist-info/top_level.txt
lxparse-1.0.8.dist-info/RECORD
