Metadata-Version: 2.1
Name: lxparse
Version: 1.0.8
Summary: A library for intelligently parsing list page links and details page contents
Home-page: https://github.com/lixi5338619/lxparse
Author: lx
Author-email: 125066648@qq.com
Maintainer: lx
License: UNKNOWN
Keywords: python web crawl HtmlParse
Platform: all
Classifier: Programming Language :: Python :: 3
Requires-Python: >=3.6
Requires-Dist: lxml
Requires-Dist: lxpy
Requires-Dist: chardet
